gradgraph/__init__.py
gradgraph/graph/__init__.py
gradgraph/graph/features.py
gradgraph/graph/hash.py
gradgraph/graph/paths.py
gradgraph/graph/persistence.py
gradgraph/graph/utils.py
gradgraph/optimization/__init__.py
gradgraph/optimization/tf/__init__.py
gradgraph/optimization/tf/callbacks.py
gradgraph/optimization/tf/constraints.py
gradgraph/optimization/tf/interp.py
gradgraph/optimization/tf/layers.py
gradgraph/optimization/tf/trainer.py
gradgraph/optimization/tf/utils.py
gradgraph-0.0.2.dist-info/licenses/LICENSE
gradgraph-0.0.2.dist-info/METADATA
gradgraph-0.0.2.dist-info/WHEEL
gradgraph-0.0.2.dist-info/top_level.txt
gradgraph-0.0.2.dist-info/RECORD
