Metadata-Version: 2.4
Name: gradgraph
Version: 0.0.2
Summary: Core library for graph-structured parameter optimization via gradient methods.
Author-email: Nicolas Fricker <nicolas.fricker@univ-cotedazur.fr>
Project-URL: Homepage, https://github.com/Fricker95/gradgraph
Project-URL: Issues, https://github.com/Fricker95/gradgraph/issues
Project-URL: Documentation, https://gradgraph.readthedocs.io/en/latest/
Classifier: Programming Language :: Python :: 3
Classifier: Operating System :: OS Independent
Classifier: Intended Audience :: Science/Research
Classifier: Topic :: Scientific/Engineering :: Bio-Informatics
Requires-Python: >=3.11
License-File: LICENSE
Requires-Dist: gudhi>=3.10.1
Requires-Dist: h5py>=3.10.0
Requires-Dist: matplotlib>=3.8.2
Requires-Dist: networkx>=3.4.2
Requires-Dist: numpy>=1.26.4
Requires-Dist: orjson>=3.10.12
Requires-Dist: scipy>=1.11.4
Requires-Dist: tensorflow>=2.16.1
Requires-Dist: keras>=3.1.1
Requires-Dist: tqdm>=4.67.1
Provides-Extra: dev
Requires-Dist: pytest; extra == "dev"
Requires-Dist: flake8; extra == "dev"
Requires-Dist: sphinx; extra == "dev"
Dynamic: license-file
